ultracontext/__init__.py
ultracontext/client.py
ultracontext/exceptions.py
ultracontext/py.typed
ultracontext/types.py
ultracontext-1.0.2.dist-info/METADATA
ultracontext-1.0.2.dist-info/WHEEL
ultracontext-1.0.2.dist-info/licenses/LICENSE
ultracontext-1.0.2.dist-info/RECORD
