Metadata-Version: 2.4
Name: ultracontext
Version: 1.0.2
Summary: The context API for AI agents
Project-URL: Homepage, https://ultracontext.ai
Project-URL: Documentation, https://ultracontext.ai/docs
Project-URL: Repository, https://github.com/ultracontext/ultracontext-python
Author-email: UltraContext <fabio@ultracontext.ai>
License-Expression: MIT
License-File: LICENSE
Keywords: agents,ai,api,context,llm
Classifier: Development Status :: 5 - Production/Stable
Classifier: Intended Audience :: Developers
Classifier: License :: OSI Approved :: MIT License
Classifier: Programming Language :: Python :: 3
Classifier: Programming Language :: Python :: 3.8
Classifier: Programming Language :: Python :: 3.9
Classifier: Programming Language :: Python :: 3.10
Classifier: Programming Language :: Python :: 3.11
Classifier: Programming Language :: Python :: 3.12
Classifier: Programming Language :: Python :: 3.13
Classifier: Typing :: Typed
Requires-Python: >=3.8
Requires-Dist: httpx>=0.24.0
Provides-Extra: dev
Requires-Dist: mypy>=1.0.0; extra == 'dev'
Requires-Dist: pytest-asyncio>=0.21.0; extra == 'dev'
Requires-Dist: pytest>=7.0.0; extra == 'dev'
